optimal_buy_cbpro/__init__.py
optimal_buy_cbpro/history.py
optimal_buy_cbpro/optimal_buy_cbpro.py
tests/__init__.py
tests/test_optimal_buy_cbpro.py
optimal_buy_cbpro-1.1.22.dist-info/LICENSE
optimal_buy_cbpro-1.1.22.dist-info/METADATA
optimal_buy_cbpro-1.1.22.dist-info/WHEEL
optimal_buy_cbpro-1.1.22.dist-info/entry_points.txt
optimal_buy_cbpro-1.1.22.dist-info/top_level.txt
optimal_buy_cbpro-1.1.22.dist-info/RECORD
