Metadata-Version: 2.1
Name: optimal-buy-cbpro
Version: 1.1.22
Summary: Buy the coins, optimally!
Home-page: https://github.com/brndnmtthws/optimal-buy-cbpro
Author: Brenden Matthews
Author-email: brenden@diddyinc.com
Classifier: Programming Language :: Python :: 3
Classifier: License :: Public Domain
Classifier: Operating System :: OS Independent
Requires-Python: >=3.5
License-File: LICENSE
Requires-Dist: cbpro-notbroken (==1.1.5)
Requires-Dist: sqlalchemy (>=1.2.14)
Requires-Dist: python-dateutil (>=2.7.5)
Requires-Dist: requests (>=2.21.0)
Provides-Extra: test
Requires-Dist: pytest-cov ; extra == 'test'
Requires-Dist: pytest (>=3.5.0) ; extra == 'test'
